{"flowContents":{"identifier":"968b238c-95f3-354c-93b4-70fd6cb087fa","instanceIdentifier":"0d0693f0-2c57-38bf-1da4-f5e9ee1a6fb1","name":"Transit Pulsar","comments":"","position":{"x":1309.0,"y":2804.0},"processGroups":[],"remoteProcessGroups":[],"processors":[{"identifier":"f3943b61-08ef-37cc-bb3a-90da9c1a718b","instanceIdentifier":"870d2073-5634-3908-dfc2-5e9105bf4d34","name":"Dynamic Topic","comments":"","position":{"x":-512.0,"y":272.0},"type":"org.apache.nifi.processors.attributes.UpdateAttribute","bundle":{"group":"org.apache.nifi","artifact":"nifi-update-attribute-nar","version":"1.18.0"},"properties":{"Delete Attributes Expression":null,"Store State":"Do not store state","canonical-value-lookup-cache-size":"100","topic":"${companyName:append(${serviceName})} ","Stateful Variables Initial Value":null},"propertyDescriptors":{"Delete Attributes Expression":{"name":"Delete Attributes Expression","displayName":"Delete Attributes Expression","identifiesControllerService":false,"sensitive":false},"Store State":{"name":"Store State","displayName":"Store State","identifiesControllerService":false,"sensitive":false},"canonical-value-lookup-cache-size":{"name":"canonical-value-lookup-cache-size","displayName":"Cache Value Lookup Cache Size","identifiesControllerService":false,"sensitive":false},"topic":{"name":"topic","displayName":"topic","identifiesControllerService":false,"sensitive":false},"Stateful Variables Initial Value":{"name":"Stateful Variables Initial Value","displayName":"Stateful Variables Initial Value","identifiesControllerService":false,"sensitive":false}},"style":{},"schedulingPeriod":"0 sec","schedulingStrategy":"TIMER_DRIVEN","executionNode":"ALL","penaltyDuration":"30 sec","yieldDuration":"1 sec","bulletinLevel":"WARN","runDurationMillis":0,"concurrentlySchedulableTaskCount":1,"autoTerminatedRelationships":[],"scheduledState":"ENABLED","retryCount":0,"retriedRelationships":[],"backoffMechanism":"PENALIZE_FLOWFILE","maxBackoffPeriod":"10 mins","componentType":"PROCESSOR","groupIdentifier":"968b238c-95f3-354c-93b4-70fd6cb087fa"},{"identifier":"d2f1b571-f9e2-3b39-aade-0da818f9ffd3","instanceIdentifier":"c8de74e8-401c-3a63-cbe5-6a96980bec8d","name":"RetryFlowFile","comments":"","position":{"x":-512.0,"y":696.0},"type":"org.apache.nifi.processors.standard.RetryFlowFile","bundle":{"group":"org.apache.nifi","artifact":"nifi-standard-nar","version":"1.18.0"},"properties":{"penalize-retries":"true","maximum-retries":"3","Fail on Non-numerical Overwrite":"false","reuse-mode":"fail","retry-attribute":"flowfile.retries"},"propertyDescriptors":{"penalize-retries":{"name":"penalize-retries","displayName":"Penalize Retries","identifiesControllerService":false,"sensitive":false},"maximum-retries":{"name":"maximum-retries","displayName":"Maximum Retries","identifiesControllerService":false,"sensitive":false},"Fail on Non-numerical Overwrite":{"name":"Fail on Non-numerical Overwrite","displayName":"Fail on Non-numerical Overwrite","identifiesControllerService":false,"sensitive":false},"reuse-mode":{"name":"reuse-mode","displayName":"Reuse Mode","identifiesControllerService":false,"sensitive":false},"retry-attribute":{"name":"retry-attribute","displayName":"Retry Attribute","identifiesControllerService":false,"sensitive":false}},"style":{},"schedulingPeriod":"0 sec","schedulingStrategy":"TIMER_DRIVEN","executionNode":"ALL","penaltyDuration":"30 sec","yieldDuration":"1 sec","bulletinLevel":"WARN","runDurationMillis":0,"concurrentlySchedulableTaskCount":1,"autoTerminatedRelationships":[],"scheduledState":"ENABLED","retryCount":0,"retriedRelationships":[],"backoffMechanism":"PENALIZE_FLOWFILE","maxBackoffPeriod":"10 mins","componentType":"PROCESSOR","groupIdentifier":"968b238c-95f3-354c-93b4-70fd6cb087fa"},{"identifier":"73cfaa74-8345-3c0b-9e91-8336eb81e489","instanceIdentifier":"e7b10226-0183-1000-dc06-f2410eac4c2f","name":"PublishPulsarRecord","comments":"","position":{"x":-512.0,"y":480.0},"type":"org.apache.nifi.processors.pulsar.pubsub.PublishPulsarRecord","bundle":{"group":"io.streamnative.connectors","artifact":"nifi-pulsar-nar","version":"1.18.0"},"properties":{"MAX_ASYNC_REQUESTS":"50","BATCH_INTERVAL":"10 ms","COMPRESSION_TYPE":"NONE","PULSAR_CLIENT_SERVICE":"6fb6d84f-defc-3649-a872-ffb6c0efa239","MESSAGE_ROUTING_MODE":"RoundRobinPartition","RECORD_WRITER":"232410b0-1f63-3031-96b8-aeec25a231e2","BLOCK_IF_QUEUE_FULL":"false","BATCHING_MAX_MESSAGES":"1000","MAPPED_MESSAGE_PROPERTIES":"","PENDING_MAX_MESSAGES":"5000","TOPIC":"${topic}","MESSAGE_DEMARCATOR":null,"ASYNC_ENABLED":"false","RECORD_READER":"cd4bcd7d-1029-3bb7-b349-a412f213be55","MESSAGE_KEY":"${uuid}","BATCHING_ENABLED":"false"},"propertyDescriptors":{"MAX_ASYNC_REQUESTS":{"name":"MAX_ASYNC_REQUESTS","displayName":"Maximum Async Requests","identifiesControllerService":false,"sensitive":false},"BATCH_INTERVAL":{"name":"BATCH_INTERVAL","displayName":"Batch Interval","identifiesControllerService":false,"sensitive":false},"COMPRESSION_TYPE":{"name":"COMPRESSION_TYPE","displayName":"Compression Type","identifiesControllerService":false,"sensitive":false},"PULSAR_CLIENT_SERVICE":{"name":"PULSAR_CLIENT_SERVICE","displayName":"Pulsar Client Service","identifiesControllerService":true,"sensitive":false},"MESSAGE_ROUTING_MODE":{"name":"MESSAGE_ROUTING_MODE","displayName":"Message Routing Mode","identifiesControllerService":false,"sensitive":false},"RECORD_WRITER":{"name":"RECORD_WRITER","displayName":"Record Writer","identifiesControllerService":true,"sensitive":false},"BLOCK_IF_QUEUE_FULL":{"name":"BLOCK_IF_QUEUE_FULL","displayName":"Block if Message Queue Full","identifiesControllerService":false,"sensitive":false},"BATCHING_MAX_MESSAGES":{"name":"BATCHING_MAX_MESSAGES","displayName":"Batching Max Messages","identifiesControllerService":false,"sensitive":false},"MAPPED_MESSAGE_PROPERTIES":{"name":"MAPPED_MESSAGE_PROPERTIES","displayName":"Mapped Message Properties","identifiesControllerService":false,"sensitive":false},"PENDING_MAX_MESSAGES":{"name":"PENDING_MAX_MESSAGES","displayName":"Max Pending Messages","identifiesControllerService":false,"sensitive":false},"TOPIC":{"name":"TOPIC","displayName":"Topic Name","identifiesControllerService":false,"sensitive":false},"MESSAGE_DEMARCATOR":{"name":"MESSAGE_DEMARCATOR","displayName":"Message Demarcator","identifiesControllerService":false,"sensitive":false},"ASYNC_ENABLED":{"name":"ASYNC_ENABLED","displayName":"Async Enabled","identifiesControllerService":false,"sensitive":false},"RECORD_READER":{"name":"RECORD_READER","displayName":"Record Reader","identifiesControllerService":true,"sensitive":false},"MESSAGE_KEY":{"name":"MESSAGE_KEY","displayName":"Message Key","identifiesControllerService":false,"sensitive":false},"BATCHING_ENABLED":{"name":"BATCHING_ENABLED","displayName":"Batching Enabled","identifiesControllerService":false,"sensitive":false}},"style":{},"schedulingPeriod":"0 sec","schedulingStrategy":"TIMER_DRIVEN","executionNode":"ALL","penaltyDuration":"30 sec","yieldDuration":"1 sec","bulletinLevel":"ERROR","runDurationMillis":0,"concurrentlySchedulableTaskCount":1,"autoTerminatedRelationships":[],"scheduledState":"ENABLED","retryCount":10,"retriedRelationships":[],"backoffMechanism":"PENALIZE_FLOWFILE","maxBackoffPeriod":"10 mins","componentType":"PROCESSOR","groupIdentifier":"968b238c-95f3-354c-93b4-70fd6cb087fa"}],"inputPorts":[{"identifier":"e6660352-7a2b-361e-835a-8c04cd85ab14","instanceIdentifier":"483e257e-939e-3c5a-eeeb-fbb42b6f975e","name":"JSON IN","comments":"","position":{"x":-464.0,"y":144.0},"type":"INPUT_PORT","concurrentlySchedulableTaskCount":1,"scheduledState":"ENABLED","allowRemoteAccess":false,"componentType":"INPUT_PORT","groupIdentifier":"968b238c-95f3-354c-93b4-70fd6cb087fa"},{"identifier":"a422bd6d-2754-31e7-ae67-9438cc29ac13","instanceIdentifier":"c2a27332-f200-3fff-0011-f84405552481","name":"Direct In","comments":"","position":{"x":72.0,"y":336.0},"type":"INPUT_PORT","concurrentlySchedulableTaskCount":1,"scheduledState":"ENABLED","allowRemoteAccess":false,"componentType":"INPUT_PORT","groupIdentifier":"968b238c-95f3-354c-93b4-70fd6cb087fa"}],"outputPorts":[{"identifier":"7f6c4e53-126a-3e4b-a05f-eecb9889a448","instanceIdentifier":"50b02a09-5fc9-3b52-a45a-7a1084f4c9e2","name":"Errors Out","comments":"","position":{"x":-552.0,"y":952.0},"type":"OUTPUT_PORT","concurrentlySchedulableTaskCount":1,"scheduledState":"ENABLED","allowRemoteAccess":false,"componentType":"OUTPUT_PORT","groupIdentifier":"968b238c-95f3-354c-93b4-70fd6cb087fa"}],"connections":[{"identifier":"39609613-1917-3b0f-8e1c-9fa500ae83f6","instanceIdentifier":"f0c46120-0183-1000-d656-e3888421cc58","name":"","source":{"id":"a422bd6d-2754-31e7-ae67-9438cc29ac13","type":"INPUT_PORT","groupId":"968b238c-95f3-354c-93b4-70fd6cb087fa","name":"Direct In","comments":"","instanceIdentifier":"c2a27332-f200-3fff-0011-f84405552481"},"destination":{"id":"73cfaa74-8345-3c0b-9e91-8336eb81e489","type":"PROCESSOR","groupId":"968b238c-95f3-354c-93b4-70fd6cb087fa","name":"PublishPulsarRecord","comments":"","instanceIdentifier":"e7b10226-0183-1000-dc06-f2410eac4c2f"},"labelIndex":1,"zIndex":0,"selectedRelationships":[""],"backPressureObjectThreshold":999999,"backPressureDataSizeThreshold":"1 GB","flowFileExpiration":"0 sec","prioritizers":[],"bends":[],"loadBalanceStrategy":"DO_NOT_LOAD_BALANCE","partitioningAttribute":"","loadBalanceCompression":"DO_NOT_COMPRESS","componentType":"CONNECTION","groupIdentifier":"968b238c-95f3-354c-93b4-70fd6cb087fa"},{"identifier":"8eb658d9-46f6-364f-a12b-64a533fa697c","instanceIdentifier":"f6bd6b70-0183-1000-5eba-e40c4220a735","name":"","source":{"id":"d2f1b571-f9e2-3b39-aade-0da818f9ffd3","type":"PROCESSOR","groupId":"968b238c-95f3-354c-93b4-70fd6cb087fa","name":"RetryFlowFile","comments":"","instanceIdentifier":"c8de74e8-401c-3a63-cbe5-6a96980bec8d"},"destination":{"id":"73cfaa74-8345-3c0b-9e91-8336eb81e489","type":"PROCESSOR","groupId":"968b238c-95f3-354c-93b4-70fd6cb087fa","name":"PublishPulsarRecord","comments":"","instanceIdentifier":"e7b10226-0183-1000-dc06-f2410eac4c2f"},"labelIndex":1,"zIndex":0,"selectedRelationships":["retry"],"backPressureObjectThreshold":999999,"backPressureDataSizeThreshold":"1 GB","flowFileExpiration":"0 sec","prioritizers":[],"bends":[{"x":-80.0,"y":656.0}],"loadBalanceStrategy":"DO_NOT_LOAD_BALANCE","partitioningAttribute":"","loadBalanceCompression":"DO_NOT_COMPRESS","componentType":"CONNECTION","groupIdentifier":"968b238c-95f3-354c-93b4-70fd6cb087fa"},{"identifier":"2c076e77-6c1b-33b2-9c39-667a4e7c81f1","instanceIdentifier":"c47910a1-20e5-3bd9-4fac-0aea675ba2e3","name":"","source":{"id":"f3943b61-08ef-37cc-bb3a-90da9c1a718b","type":"PROCESSOR","groupId":"968b238c-95f3-354c-93b4-70fd6cb087fa","name":"Dynamic Topic","comments":"","instanceIdentifier":"870d2073-5634-3908-dfc2-5e9105bf4d34"},"destination":{"id":"73cfaa74-8345-3c0b-9e91-8336eb81e489","type":"PROCESSOR","groupId":"968b238c-95f3-354c-93b4-70fd6cb087fa","name":"PublishPulsarRecord","comments":"","instanceIdentifier":"e7b10226-0183-1000-dc06-f2410eac4c2f"},"labelIndex":1,"zIndex":0,"selectedRelationships":["success"],"backPressureObjectThreshold":999999,"backPressureDataSizeThreshold":"1 GB","flowFileExpiration":"0 sec","prioritizers":[],"bends":[],"loadBalanceStrategy":"DO_NOT_LOAD_BALANCE","partitioningAttribute":"","loadBalanceCompression":"DO_NOT_COMPRESS","componentType":"CONNECTION","groupIdentifier":"968b238c-95f3-354c-93b4-70fd6cb087fa"},{"identifier":"175eb699-4eea-321a-a2ed-61ba02089197","instanceIdentifier":"e7b2fe78-0183-1000-496a-08acc112d4cf","name":"","source":{"id":"73cfaa74-8345-3c0b-9e91-8336eb81e489","type":"PROCESSOR","groupId":"968b238c-95f3-354c-93b4-70fd6cb087fa","name":"PublishPulsarRecord","comments":"","instanceIdentifier":"e7b10226-0183-1000-dc06-f2410eac4c2f"},"destination":{"id":"398908e3-cc81-3878-ba8d-3e9e0596cd1e","type":"FUNNEL","groupId":"968b238c-95f3-354c-93b4-70fd6cb087fa","name":"Funnel","comments":"","instanceIdentifier":"e7b2ef28-0183-1000-2903-5b77490708be"},"labelIndex":1,"zIndex":0,"selectedRelationships":["success"],"backPressureObjectThreshold":999999,"backPressureDataSizeThreshold":"1 GB","flowFileExpiration":"0 sec","prioritizers":[],"bends":[],"loadBalanceStrategy":"DO_NOT_LOAD_BALANCE","partitioningAttribute":"","loadBalanceCompression":"DO_NOT_COMPRESS","componentType":"CONNECTION","groupIdentifier":"968b238c-95f3-354c-93b4-70fd6cb087fa"},{"identifier":"4b7cb7a7-0bbd-3fdc-a3a3-daf61b68b654","instanceIdentifier":"698fe353-32aa-31b3-1bb3-957f586479fe","name":"","source":{"id":"e6660352-7a2b-361e-835a-8c04cd85ab14","type":"INPUT_PORT","groupId":"968b238c-95f3-354c-93b4-70fd6cb087fa","name":"JSON IN","comments":"","instanceIdentifier":"483e257e-939e-3c5a-eeeb-fbb42b6f975e"},"destination":{"id":"f3943b61-08ef-37cc-bb3a-90da9c1a718b","type":"PROCESSOR","groupId":"968b238c-95f3-354c-93b4-70fd6cb087fa","name":"Dynamic Topic","comments":"","instanceIdentifier":"870d2073-5634-3908-dfc2-5e9105bf4d34"},"labelIndex":1,"zIndex":0,"selectedRelationships":[""],"backPressureObjectThreshold":2000000,"backPressureDataSizeThreshold":"1 GB","flowFileExpiration":"0 sec","prioritizers":[],"bends":[],"loadBalanceStrategy":"DO_NOT_LOAD_BALANCE","partitioningAttribute":"","loadBalanceCompression":"DO_NOT_COMPRESS","componentType":"CONNECTION","groupIdentifier":"968b238c-95f3-354c-93b4-70fd6cb087fa"},{"identifier":"305b476c-aacd-379c-8281-3886a964b428","instanceIdentifier":"1dd7e598-8aba-3c6f-c33f-abccd195e0d4","name":"","source":{"id":"d2f1b571-f9e2-3b39-aade-0da818f9ffd3","type":"PROCESSOR","groupId":"968b238c-95f3-354c-93b4-70fd6cb087fa","name":"RetryFlowFile","comments":"","instanceIdentifier":"c8de74e8-401c-3a63-cbe5-6a96980bec8d"},"destination":{"id":"7f6c4e53-126a-3e4b-a05f-eecb9889a448","type":"OUTPUT_PORT","groupId":"968b238c-95f3-354c-93b4-70fd6cb087fa","name":"Errors Out","comments":"","instanceIdentifier":"50b02a09-5fc9-3b52-a45a-7a1084f4c9e2"},"labelIndex":1,"zIndex":0,"selectedRelationships":["retries_exceeded","failure"],"backPressureObjectThreshold":10000,"backPressureDataSizeThreshold":"1 GB","flowFileExpiration":"0 sec","prioritizers":[],"bends":[],"loadBalanceStrategy":"DO_NOT_LOAD_BALANCE","partitioningAttribute":"","loadBalanceCompression":"DO_NOT_COMPRESS","componentType":"CONNECTION","groupIdentifier":"968b238c-95f3-354c-93b4-70fd6cb087fa"},{"identifier":"0cbbba43-0860-3a46-963e-bdde4c273fd3","instanceIdentifier":"e7b156e3-0183-1000-f643-43972d5c3251","name":"","source":{"id":"73cfaa74-8345-3c0b-9e91-8336eb81e489","type":"PROCESSOR","groupId":"968b238c-95f3-354c-93b4-70fd6cb087fa","name":"PublishPulsarRecord","comments":"","instanceIdentifier":"e7b10226-0183-1000-dc06-f2410eac4c2f"},"destination":{"id":"d2f1b571-f9e2-3b39-aade-0da818f9ffd3","type":"PROCESSOR","groupId":"968b238c-95f3-354c-93b4-70fd6cb087fa","name":"RetryFlowFile","comments":"","instanceIdentifier":"c8de74e8-401c-3a63-cbe5-6a96980bec8d"},"labelIndex":1,"zIndex":0,"selectedRelationships":["failure"],"backPressureObjectThreshold":999999,"backPressureDataSizeThreshold":"1 GB","flowFileExpiration":"0 sec","prioritizers":[],"bends":[],"loadBalanceStrategy":"DO_NOT_LOAD_BALANCE","partitioningAttribute":"","loadBalanceCompression":"DO_NOT_COMPRESS","componentType":"CONNECTION","groupIdentifier":"968b238c-95f3-354c-93b4-70fd6cb087fa"}],"labels":[],"funnels":[{"identifier":"398908e3-cc81-3878-ba8d-3e9e0596cd1e","instanceIdentifier":"e7b2ef28-0183-1000-2903-5b77490708be","position":{"x":-880.0,"y":672.0},"componentType":"FUNNEL","groupIdentifier":"968b238c-95f3-354c-93b4-70fd6cb087fa"}],"controllerServices":[],"variables":{},"defaultFlowFileExpiration":"0 sec","defaultBackPressureObjectThreshold":999999,"defaultBackPressureDataSizeThreshold":"1 GB","componentType":"PROCESS_GROUP","flowFileConcurrency":"UNBOUNDED","flowFileOutboundPolicy":"STREAM_WHEN_AVAILABLE"},"externalControllerServices":{"232410b0-1f63-3031-96b8-aeec25a231e2":{"identifier":"232410b0-1f63-3031-96b8-aeec25a231e2","name":"Standard Inherit JsonRecordSetWriter"},"cd4bcd7d-1029-3bb7-b349-a412f213be55":{"identifier":"cd4bcd7d-1029-3bb7-b349-a412f213be55","name":"CDP Infer JsonTreeReader"},"6fb6d84f-defc-3649-a872-ffb6c0efa239":{"identifier":"6fb6d84f-defc-3649-a872-ffb6c0efa239","name":"StandalonePulsarLocal118"}},"parameterContexts":{},"flowEncodingVersion":"1.0","parameterProviders":{},"latest":false}